Metadata-Version: 2.1
Name: streetaddress
Version: 0.1.4
Summary: A Python port of the Perl address parser.
Home-page: https://github.com/ArcadiaPower/python-streetaddress
Author: Mike Jensen
Keywords: streetaddress
Classifier: Development Status :: 5 - Production/Stable
Classifier: Environment :: Other Environment
Classifier: Intended Audience :: Developers
Classifier: Natural Language :: English
Classifier: Operating System :: MacOS :: MacOS X
Classifier: Operating System :: Microsoft :: Windows
Classifier: Operating System :: POSIX
Classifier: Programming Language :: Python :: 3
Classifier: Programming Language :: Python :: 3.7
Classifier: Programming Language :: Python :: 3.8
Classifier: Programming Language :: Python :: 3.9
Classifier: Programming Language :: Python :: 3.10
Classifier: Topic :: Security
License-File: LICENSE
License-File: AUTHORS.rst
